domolibrary/__init__.py
domolibrary/_modidx.py
domolibrary/classes/CodeEngineManifest.py
domolibrary/classes/CodeEngineManifest_Argument.py
domolibrary/classes/CodeEngineManifest_Function.py
domolibrary/classes/DomoAccess.py
domolibrary/classes/DomoAccessToken.py
domolibrary/classes/DomoAccount.py
domolibrary/classes/DomoAccount_Config.py
domolibrary/classes/DomoAccount_Credential.py
domolibrary/classes/DomoAccount_Default.py
domolibrary/classes/DomoAccount_OAuth.py
domolibrary/classes/DomoActivityLog.py
domolibrary/classes/DomoAllowlist.py
domolibrary/classes/DomoAppDb.py
domolibrary/classes/DomoAppStudio.py
domolibrary/classes/DomoApplication.py
domolibrary/classes/DomoApplication_Job.py
domolibrary/classes/DomoApplication_Job_Base.py
domolibrary/classes/DomoApplication_Job_RemoteDomoStats.py
domolibrary/classes/DomoApplication_Job_Watchdog.py
domolibrary/classes/DomoBootstrap.py
domolibrary/classes/DomoCard.py
domolibrary/classes/DomoCertification.py
domolibrary/classes/DomoCodeEngine.py
domolibrary/classes/DomoDatacenter.py
domolibrary/classes/DomoDataflow.py
domolibrary/classes/DomoDataflow_Action.py
domolibrary/classes/DomoDataflow_History.py
domolibrary/classes/DomoDataset.py
domolibrary/classes/DomoDataset_Connector.py
domolibrary/classes/DomoDataset_Schema.py
domolibrary/classes/DomoDataset_Stream.py
domolibrary/classes/DomoGrant.py
domolibrary/classes/DomoGroup.py
domolibrary/classes/DomoInstanceConfig.py
domolibrary/classes/DomoInstanceConfig_ApiClient.py
domolibrary/classes/DomoInstanceConfig_InstanceSwitcher.py
domolibrary/classes/DomoInstanceConfig_MFA.py
domolibrary/classes/DomoInstanceConfig_SSO.py
domolibrary/classes/DomoInstanceConfig_UserAttribute.py
domolibrary/classes/DomoIntegration.py
domolibrary/classes/DomoJupyter.py
domolibrary/classes/DomoJupyter_Account.py
domolibrary/classes/DomoJupyter_Content.py
domolibrary/classes/DomoJupyter_DataSource.py
domolibrary/classes/DomoLineage.py
domolibrary/classes/DomoMembership.py
domolibrary-4.5.28.dist-info/licenses/LICENSE
domolibrary-4.5.28.dist-info/METADATA
domolibrary-4.5.28.dist-info/WHEEL
domolibrary-4.5.28.dist-info/entry_points.txt
domolibrary-4.5.28.dist-info/top_level.txt
domolibrary-4.5.28.dist-info/RECORD
