Metadata-Version: 2.4
Name: domolibrary
Version: 4.5.28
Home-page: https://github.com/jaewilson07/domo_library
Author: Jae Wilson
Author-email: jaewilson07@gmail.com
License: Apache Software License 2.0
Keywords: nbdev jupyter notebook python
Classifier: Development Status :: 4 - Beta
Classifier: Intended Audience :: Developers
Classifier: Natural Language :: English
Classifier: Programming Language :: Python :: 3.9
Classifier: Programming Language :: Python :: 3.10
Classifier: License :: OSI Approved :: Apache Software License
Requires-Python: >=3.9
License-File: LICENSE
Requires-Dist: nbdev
Requires-Dist: pandas
Requires-Dist: aiohttp
Requires-Dist: requests
Requires-Dist: twine
Requires-Dist: orjson
Requires-Dist: httpx
Requires-Dist: python-dotenv
Requires-Dist: sqlparse
Requires-Dist: sqlglot
Requires-Dist: bs4
Requires-Dist: nbqa
Requires-Dist: black
Requires-Dist: aenum
Requires-Dist: pillow
Requires-Dist: xkcdpass
Requires-Dist: sql_metadata
Provides-Extra: dev
Dynamic: author
Dynamic: author-email
Dynamic: classifier
Dynamic: description
Dynamic: description-content-type
Dynamic: home-page
Dynamic: keywords
Dynamic: license
Dynamic: license-file
Dynamic: provides-extra
Dynamic: requires-dist
Dynamic: requires-python
